cli_bob/__init__.py
cli_bob/_endpoints.py
cli_bob/_terminal.py
cli_bob/_utilities.py
cli_bob-0.2.1.dist-info/licenses/LICENSE
cli_bob-0.2.1.dist-info/METADATA
cli_bob-0.2.1.dist-info/WHEEL
cli_bob-0.2.1.dist-info/entry_points.txt
cli_bob-0.2.1.dist-info/top_level.txt
cli_bob-0.2.1.dist-info/RECORD
