Metadata-Version: 2.4
Name: cli-bob
Version: 0.2.1
Summary: cli-bob uses AI to generate command line code in case you cannot remember the exact syntax.
Home-page: https://github.com/haesleinhuepf/cli-bob
Author: Robert Haase
Author-email: robert.haase@uni-leipzig.de
License: BSD-3-Clause
Project-URL: Bug Tracker, https://github.com/haesleinhuepf/cli-bob/issues
Project-URL: Documentation, https://github.com/haesleinhuepf/cli-bob#README.md
Project-URL: Source Code, https://github.com/haesleinhuepf/cli-bob
Project-URL: User Support, https://github.com/haesleinhuepf/cli-bob/issues
Classifier: Development Status :: 2 - Pre-Alpha
Classifier: Intended Audience :: Developers
Classifier: License :: OSI Approved :: BSD License
Classifier: Operating System :: OS Independent
Classifier: Programming Language :: Python
Classifier: Programming Language :: Python :: 3
Classifier: Programming Language :: Python :: 3.9
Classifier: Programming Language :: Python :: 3.10
Classifier: Programming Language :: Python :: 3.11
Requires-Python: >=3.9
License-File: LICENSE
Requires-Dist: anthropic
Requires-Dist: openai
Provides-Extra: testing
Requires-Dist: tox; extra == "testing"
Requires-Dist: pytest; extra == "testing"
Requires-Dist: pytest-cov; extra == "testing"
Dynamic: license-file
